<annotation>
<folder>sentetik/</folder>
<filename>10772939519397.jpg</filename>
<path>c:/sentetik/10772939519397.jpg</path>
<source>
		<database>Unknown</database>
	</source>
<size>
		<width>1920</width>
		<height>900</height>
		<depth>3</depth>
	</size>
<segmented>0</segmented>


<object>
		<name>arac</name>
		<pose>Unspecified</pose>
		<truncated>0</truncated>
		<difficult>0</difficult>
		<bndbox>
			<xmin>822</xmin>
			<ymin>973</ymin>
			<xmax>894</xmax>
			<ymax>1005</ymax>
		</bndbox>
	</object>
<object>
		<name>arac</name>
		<pose>Unspecified</pose>
		<truncated>0</truncated>
		<difficult>0</difficult>
		<bndbox>
			<xmin>1081</xmin>
			<ymin>33</ymin>
			<xmax>1197</xmax>
			<ymax>179</ymax>
		</bndbox>
	</object>
<object>
		<name>arac</name>
		<pose>Unspecified</pose>
		<truncated>0</truncated>
		<difficult>0</difficult>
		<bndbox>
			<xmin>1873</xmin>
			<ymin>888</ymin>
			<xmax>1918</xmax>
			<ymax>975</ymax>
		</bndbox>
	</object>
</annotation>