<annotation>
<folder>sentetik/</folder>
<filename>10823779078727.jpg</filename>
<path>c:/sentetik/10823779078727.jpg</path>
<source>
		<database>Unknown</database>
	</source>
<size>
		<width>1920</width>
		<height>900</height>
		<depth>3</depth>
	</size>
<segmented>0</segmented>


<object>
		<name>arac</name>
		<pose>Unspecified</pose>
		<truncated>0</truncated>
		<difficult>0</difficult>
		<bndbox>
			<xmin>1656</xmin>
			<ymin>643</ymin>
			<xmax>1748</xmax>
			<ymax>683</ymax>
		</bndbox>
	</object>
<object>
		<name>arac</name>
		<pose>Unspecified</pose>
		<truncated>0</truncated>
		<difficult>0</difficult>
		<bndbox>
			<xmin>24</xmin>
			<ymin>182</ymin>
			<xmax>90</xmax>
			<ymax>212</ymax>
		</bndbox>
	</object>
<object>
		<name>arac</name>
		<pose>Unspecified</pose>
		<truncated>0</truncated>
		<difficult>0</difficult>
		<bndbox>
			<xmin>747</xmin>
			<ymin>369</ymin>
			<xmax>825</xmax>
			<ymax>412</ymax>
		</bndbox>
	</object>
</annotation>